LazyDB-0.1.70.dist-info/DESCRIPTION.rst
LazyDB-0.1.70.dist-info/METADATA
LazyDB-0.1.70.dist-info/WHEEL
LazyDB-0.1.70.dist-info/top_level.txt
LazyDB-0.1.70.dist-info/metadata.json
LazyDB-0.1.70.dist-info/RECORD
lazydb/utils.py
lazydb/__init__.py
lazydb/lazydb.py
