Metadata-Version: 2.0
Name: LazyDB
Version: 0.1.70
Summary: LazyDB is a basic wrapper around the Python shelve flatfile dbm module.
Home-page: http://pypi.python.org/pypi/LazyDB
Author: mek
Author-email: michael.karpeles@gmail.com
License: LICENSE.txt
Platform: UNKNOWN
